stac_api_load_balancing/cli.py
stac_api_load_balancing/config_files/locustfile.py
stac_api_load_balancing/config_files/taurus_locust.yml
stac_api_load_balancing/data_loader/__init__.py
stac_api_load_balancing/data_loader/data_loader.py
stac_api_load_balancing/data_loader/setup_data/collection.json
stac_api_load_balancing/data_loader/setup_data/sentinel-s2-l2a-cogs_0_100.json
stac_api_load_balancing-0.2.0.dist-info/LICENSE
stac_api_load_balancing-0.2.0.dist-info/METADATA
stac_api_load_balancing-0.2.0.dist-info/WHEEL
stac_api_load_balancing-0.2.0.dist-info/entry_points.txt
stac_api_load_balancing-0.2.0.dist-info/top_level.txt
stac_api_load_balancing-0.2.0.dist-info/RECORD
